{
  "payment": {
    "statuses": {
      "status": [
        {
          "code": "201.0000",
          "description": "The resource was successfully created.",
          "severity": "information"
        }
      ]
    },
    "descriptor": "customer-statement",
    "notifications": {
      "notification": [
        {
          "url": "{{notification_endpoint}}"
        }
      ]
    },
    "locale": "de",
    "merchant-account-id": {
      "value": "4aeccf39-0d47-47f6-a399-c05c1f2fc819"
    },
    "transaction-id": "2639838f-c4cf-40fa-92d4-3ca770fbbea8",
    "request-id": "eef149e4-6c3d-4065-9e13-34eecf148239",
    "transaction-type": "get-url",
    "transaction-state": "success",
    "completion-time-stamp": 1572942331000,
    "requested-amount": {
      "value": 1.23,
      "currency": "EUR"
    },
    "order-number": "180516095533783",
    "payment-methods": {
      "payment-method": [
        {
          "url": "https://idealtest.secure-ing.com/ideal/issuerSim.do?trxid=0050000211299520&ideal=prob",
          "name": "ideal"
        }
      ]
    },
    "bank-account": {
      "bic": "INGBNL2A"
    },
    "cancel-redirect-url": "https://{pp-redirect-url-cancel}",
    "fail-redirect-url": "https://{pp-redirect-url-error}",
    "success-redirect-url": "https://{pp-redirect-url-success}"
  }
}