<payment xmlns="http://www.elastic-payments.com/schema/payment" xmlns:ns2="http://www.elastic-payments.com/schema/epa/transaction">
  <merchant-account-id>0518ac4e-a622-48d8-87f5-a04835ded715</merchant-account-id>
  <transaction-id>dfb68a27-65de-4682-98d2-17e83c532116</transaction-id>
  <request-id>17b0f1b1-00b1-4e14-a4c4-8f3f80a4085b</request-id>
  <transaction-type>debit</transaction-type>
  <transaction-state>failed</transaction-state>
  <completion-time-stamp>2018-10-16T09:47:30.000Z</completion-time-stamp>
  <statuses>
    <status code="400.1016" description="The Email Address is syntactically incorrect.  Please check your input and try again." severity="error"/>
  </statuses>
  <requested-amount currency="MYR">10</requested-amount>
  <account-holder>
    <first-name>John</first-name>
    <last-name>Doe</last-name>
    <email>john.doe</email>
    <phone>+123456789</phone>
  </account-holder>
  <descriptor>description</descriptor>
  <payment-methods>
    <payment-method name="fpx_abb"/>
  </payment-methods>
  <country>MY</country>
</payment>
