<payment xmlns="http://www.elastic-payments.com/schema/payment">
  <merchant-account-id>0492ac17-b459-420c-8e4d-445be229d276</merchant-account-id>
  <payment-methods>
    <payment-method name="maybank2u"/>
  </payment-methods>
  <transaction-type>get-url</transaction-type>
  <request-id>d6513abf-7a64-4a31-b773-76f19be65780</request-id>
  <requested-amount currency="MYR">100</requested-amount>
  <order-number>32168</order-number>
  <order-detail>something</order-detail>
  <account-holder>
    <first-name>John</first-name>
    <last-name>Doe</last-name>
    <email>john.doe@{domain}</email>
  </account-holder>
</payment>
